cnswd/__init__.py
cnswd/_exceptions.py
cnswd/_seleniumwire.py
cnswd/connect.py
cnswd/mongodb.py
cnswd/cninfo/__init__.py
cnswd/cninfo/base_driver.py
cnswd/cninfo/classify_tree.py
cnswd/cninfo/config.py
cnswd/cninfo/css.py
cnswd/cninfo/databrowser.py
cnswd/cninfo/ops.py
cnswd/cninfo/ts.py
cnswd/cninfo/utils.py
cnswd/scripts/__init__.py
cnswd/scripts/base.py
cnswd/scripts/category.py
cnswd/scripts/classify.py
cnswd/scripts/cninfo.py
cnswd/scripts/cninfo_meta.py
cnswd/scripts/cninfo_yypl.py
cnswd/scripts/command.py
cnswd/scripts/disclosure.py
cnswd/scripts/index_codes.py
cnswd/scripts/ptrepack.py
cnswd/scripts/sgpx.py
cnswd/scripts/sina_margin.py
cnswd/scripts/sina_news.py
cnswd/scripts/sina_quote.py
cnswd/scripts/sina_quote_index.py
cnswd/scripts/sina_tzpj.py
cnswd/scripts/sw_class.py
cnswd/scripts/tct_gn.py
cnswd/scripts/tct_minutely.py
cnswd/scripts/ths_gn.py
cnswd/scripts/ths_news.py
cnswd/scripts/trading_calendar.py
cnswd/scripts/trading_codes.py
cnswd/scripts/treasury.py
cnswd/scripts/wy_cjmx.py
cnswd/scripts/wy_cwbg.py
cnswd/scripts/wy_fhpg.py
cnswd/scripts/wy_gszl.py
cnswd/scripts/wy_index.py
cnswd/scripts/wy_quote.py
cnswd/scripts/wy_quote_index.py
cnswd/scripts/wy_stock.py
cnswd/scripts/wy_yjyg.py
cnswd/scripts/wy_zycwzb.py
cnswd/scripts/yahoo.py
cnswd/scripts/yahoo_fields.py
cnswd/scripts/yahoo_utils.py
cnswd/setting/__init__.py
cnswd/setting/config.py
cnswd/setting/constants.py
cnswd/ths/__init__.py
cnswd/ths/base.py
cnswd/ths/financial_analysis.py
cnswd/ths/hq.py
cnswd/ths/stock.py
cnswd/utils/__init__.py
cnswd/utils/cache.py
cnswd/utils/db_utils.py
cnswd/utils/dt_utils.py
cnswd/utils/log_utils.py
cnswd/utils/loop_utils.py
cnswd/utils/path_utils.py
cnswd/utils/pd_utils.py
cnswd/utils/proc_utils.py
cnswd/utils/temp.py
cnswd/utils/temp_utils.py
cnswd/utils/tools.py
cnswd/websource/__init__.py
cnswd/websource/base.py
cnswd/websource/disclosures.py
cnswd/websource/nbsc.py
cnswd/websource/sina.py
cnswd/websource/sina_news.py
cnswd/websource/sse.py
cnswd-5.0.1.dist-info/LICENSE
cnswd-5.0.1.dist-info/METADATA
cnswd-5.0.1.dist-info/WHEEL
cnswd-5.0.1.dist-info/entry_points.txt
cnswd-5.0.1.dist-info/top_level.txt
cnswd-5.0.1.dist-info/RECORD
